random_pandas/__init__.py
random_pandas/core.py
random_pandas-0.0.3.dist-info/licenses/LICENSE
random_pandas-0.0.3.dist-info/METADATA
random_pandas-0.0.3.dist-info/WHEEL
random_pandas-0.0.3.dist-info/top_level.txt
random_pandas-0.0.3.dist-info/RECORD
