Metadata-Version: 2.4
Name: random-pandas
Version: 0.0.3
Summary: A package to generate random pandas DataFrame objects and other random functionalities for machine learning benchmarking.
Author-email: Your Name <your.email@example.com>
Project-URL: Homepage, https://github.com/yourusername/random-pandas
Project-URL: Bug Tracker, https://github.com/yourusername/random-pandas/issues
Classifier: Programming Language :: Python :: 3
Classifier: License :: OSI Approved :: MIT License
Classifier: Operating System :: OS Independent
Classifier: Intended Audience :: Developers
Classifier: Intended Audience :: Science/Research
Classifier: Topic :: Scientific/Engineering :: Artificial Intelligence
Classifier: Topic :: Software Development :: Testing
Requires-Python: >=3.8
License-File: LICENSE
Requires-Dist: pandas>=1.0
Requires-Dist: numpy>=1.18
Dynamic: license-file
